inspect_magics/__init__.py
inspect_magics/magics.py
inspect_magics-2019.2.14.dist-info/LICENSE
inspect_magics-2019.2.14.dist-info/METADATA
inspect_magics-2019.2.14.dist-info/WHEEL
inspect_magics-2019.2.14.dist-info/top_level.txt
inspect_magics-2019.2.14.dist-info/RECORD
